vlcp/__init__.py
vlcp/start.py
vlcp/config/__init__.py
vlcp/config/config.py
vlcp/event/__init__.py
vlcp/event/connection.py
vlcp/event/core.py
vlcp/event/event.py
vlcp/event/future.py
vlcp/event/lock.py
vlcp/event/matchtree.py
vlcp/event/polling.py
vlcp/event/pqueue.py
vlcp/event/ratelimiter.py
vlcp/event/runnable.py
vlcp/event/stream.py
vlcp/protocol/__init__.py
vlcp/protocol/http.py
vlcp/protocol/jsonrpc.py
vlcp/protocol/ovsdb.py
vlcp/protocol/protocol.py
vlcp/protocol/raw.py
vlcp/protocol/redis.py
vlcp/protocol/zookeeper.py
vlcp/protocol/openflow/__init__.py
vlcp/protocol/openflow/openflow.py
vlcp/protocol/openflow/defs/__init__.py
vlcp/protocol/openflow/defs/common.py
vlcp/protocol/openflow/defs/definations.py
vlcp/protocol/openflow/defs/nicira_ext.py
vlcp/protocol/openflow/defs/openflow10.py
vlcp/protocol/openflow/defs/openflow13.py
vlcp/protocol/openflow/defs/openflow14.py
vlcp/scripts/__init__.py
vlcp/scripts/migratedb.py
vlcp/scripts/repairphymapdb.py
vlcp/scripts/script.py
vlcp/server/__init__.py
vlcp/server/module.py
vlcp/server/server.py
vlcp/service/__init__.py
vlcp/service/connection/__init__.py
vlcp/service/connection/httpserver.py
vlcp/service/connection/jsonrpcserver.py
vlcp/service/connection/openflowserver.py
vlcp/service/connection/redisdb.py
vlcp/service/connection/tcpserver.py
vlcp/service/connection/zookeeperdb.py
vlcp/service/debugging/__init__.py
vlcp/service/debugging/console.py
vlcp/service/kvdb/__init__.py
vlcp/service/kvdb/objectdb.py
vlcp/service/kvdb/redisnotifier.py
vlcp/service/kvdb/storage.py
vlcp/service/manage/__init__.py
vlcp/service/manage/modulemanager.py
vlcp/service/manage/webapi.py
vlcp/service/sdn/__init__.py
vlcp/service/sdn/arpresponder.py
vlcp/service/sdn/dhcpserver.py
vlcp/service/sdn/flowbase.py
vlcp/service/sdn/freearp.py
vlcp/service/sdn/icmpresponder.py
vlcp/service/sdn/ioprocessing.py
vlcp/service/sdn/l2switch.py
vlcp/service/sdn/l3router.py
vlcp/service/sdn/ofpmanager.py
vlcp/service/sdn/ofpportmanager.py
vlcp-2.2.1.dist-info/LICENSE
vlcp-2.2.1.dist-info/METADATA
vlcp-2.2.1.dist-info/WHEEL
vlcp-2.2.1.dist-info/entry_points.txt
vlcp-2.2.1.dist-info/top_level.txt
vlcp-2.2.1.dist-info/RECORD
