Metadata-Version: 2.1
Name: vlcp
Version: 2.2.1
Summary: Full stack framework for SDN Controller, support Openflow 1.0, Openflow 1.3, and Nicira extensions. Also a powerful coroutine-based web server.
Home-page: http://github.com/hubo1016/vlcp
Author: Hu Bo
Author-email: hubo1016@126.com
License: http://www.apache.org/licenses/LICENSE-2.0
Keywords: SDN,VLCP,Openflow
Platform: UNKNOWN
Requires-Python: >=3.5
Requires-Dist: nstruct (>=1.3.1)
Requires-Dist: pychecktype (>=1.4.0)
